LICENSE
MANIFEST.in
README.md
setup.py
django_img_cache.egg-info/PKG-INFO
django_img_cache.egg-info/SOURCES.txt
django_img_cache.egg-info/dependency_links.txt
django_img_cache.egg-info/not-zip-safe
django_img_cache.egg-info/requires.txt
django_img_cache.egg-info/top_level.txt
img_cache/__init__.py
img_cache/compat.py
img_cache/default.py
img_cache/helpers.py
img_cache/tests.py
img_cache/templatetags/__init__.py
img_cache/templatetags/imgcache.py
img_cache/templatetags/imgcache_tags.py